setup.py
itertoolz/__init__.py
itertoolz/compatibility.py
itertoolz/core.py
itertoolz/recipes.py
itertoolz.egg-info/PKG-INFO
itertoolz.egg-info/SOURCES.txt
itertoolz.egg-info/dependency_links.txt
itertoolz.egg-info/not-zip-safe
itertoolz.egg-info/top_level.txt