Metadata-Version: 1.0
Name: itertoolz
Version: 0.5
Summary: More iterator tools
Home-page: http://github.com/mrocklin/itertoolz
Author: Matthew Rocklin
Author-email: mrocklin@gmail.com
License: BSD
Platform: UNKNOWN
